unify_llm/__init__.py
unify_llm/client.py
unify_llm/langchain_adapter.py
unify_llm/models.py
unify_llm/utils.py
unify_llm/a2a/__init__.py
unify_llm/a2a/agent_comm.py
unify_llm/a2a/collaboration.py
unify_llm/a2a/message_bus.py
unify_llm/a2a/protocol.py
unify_llm/agent/__init__.py
unify_llm/agent/advanced.py
unify_llm/agent/base.py
unify_llm/agent/builtin_tools.py
unify_llm/agent/execution_history.py
unify_llm/agent/executor.py
unify_llm/agent/extended_tools.py
unify_llm/agent/http_tools.py
unify_llm/agent/memory.py
unify_llm/agent/monitoring.py
unify_llm/agent/templates.py
unify_llm/agent/tools.py
unify_llm/agent/triggers.py
unify_llm/agent/visualization.py
unify_llm/agent/webhook_server.py
unify_llm/agent/workflow.py
unify_llm/core/__init__.py
unify_llm/core/config.py
unify_llm/core/exceptions.py
unify_llm/core/logger.py
unify_llm/mcp/__init__.py
unify_llm/mcp/client.py
unify_llm/mcp/protocol.py
unify_llm/mcp/server.py
unify_llm/mcp/transport.py
unify_llm/providers/__init__.py
unify_llm/providers/anthropic.py
unify_llm/providers/anthropic_openai.py
unify_llm/providers/base.py
unify_llm/providers/bytedance.py
unify_llm/providers/databricks.py
unify_llm/providers/gemini.py
unify_llm/providers/grok.py
unify_llm/providers/ollama.py
unify_llm/providers/openai.py
unify_llm/providers/openrouter.py
unify_llm/providers/qwen.py
unify_llm-0.1.0.dist-info/licenses/LICENSE
unify_llm-0.1.0.dist-info/METADATA
unify_llm-0.1.0.dist-info/WHEEL
unify_llm-0.1.0.dist-info/top_level.txt
unify_llm-0.1.0.dist-info/RECORD
