Metadata-Version: 2.4
Name: unify-llm
Version: 0.1.0
Summary: A unified interface for calling various Large Language Model APIs
Author: UnifyLLM Team
License: MIT
Project-URL: Homepage, https://github.com/unifyllm/unifyllm
Project-URL: Documentation, https://unifyllm.readthedocs.io
Project-URL: Repository, https://github.com/unifyllm/unifyllm
Keywords: llm,openai,anthropic,gemini,ollama,unified-api
Classifier: Development Status :: 3 - Alpha
Classifier: Intended Audience :: Developers
Classifier: License :: OSI Approved :: MIT License
Classifier: Programming Language :: Python :: 3
Classifier: Programming Language :: Python :: 3.9
Classifier: Programming Language :: Python :: 3.10
Classifier: Programming Language :: Python :: 3.11
Classifier: Programming Language :: Python :: 3.12
Requires-Python: >=3.9
License-File: LICENSE
Requires-Dist: pydantic>=2.0.0
Requires-Dist: httpx>=0.24.0
Requires-Dist: tenacity>=8.0.0
Requires-Dist: typing-extensions>=4.5.0
Requires-Dist: python-dotenv>=1.2.1
Requires-Dist: pyyaml>=6.0.3
Requires-Dist: rootutils>=1.0.7
Requires-Dist: pydantic-settings>=2.11.0
Requires-Dist: croniter>=2.0.0
Requires-Dist: fastapi>=0.110.0
Requires-Dist: uvicorn>=0.27.0
Provides-Extra: dev
Requires-Dist: pytest>=7.0.0; extra == "dev"
Requires-Dist: pytest-asyncio>=0.21.0; extra == "dev"
Requires-Dist: pytest-cov>=4.0.0; extra == "dev"
Requires-Dist: black>=23.0.0; extra == "dev"
Requires-Dist: ruff>=0.1.0; extra == "dev"
Requires-Dist: mypy>=1.0.0; extra == "dev"
Requires-Dist: types-PyYAML>=6.0.0; extra == "dev"
Dynamic: license-file
